README.rst
bootstrap.py
buildout.cfg
mr.cabot.cfg
setup.py
src/mr/__init__.py
src/mr.cabot.egg-info/PKG-INFO
src/mr.cabot.egg-info/SOURCES.txt
src/mr.cabot.egg-info/dependency_links.txt
src/mr.cabot.egg-info/entry_points.txt
src/mr.cabot.egg-info/namespace_packages.txt
src/mr.cabot.egg-info/not-zip-safe
src/mr.cabot.egg-info/requires.txt
src/mr.cabot.egg-info/top_level.txt
src/mr/cabot/__init__.py
src/mr/cabot/git.py
src/mr/cabot/github.py
src/mr/cabot/gmane.py
src/mr/cabot/googlestaticmap.py
src/mr/cabot/html.py
src/mr/cabot/interfaces.py
src/mr/cabot/kml.py
src/mr/cabot/plone.py
src/mr/cabot/sebastian.py
src/mr/cabot/stackoverflow.py
src/mr/cabot/users.py
src/mr/cabot/tests/__init__.py