Metadata-Version: 1.0
Name: mr.cabot
Version: 1.0
Summary: A utility for finding and mapping contributions to open source projects
Home-page: http://github.com/collective/mr.cabot
Author: Matthew Wilkes
Author-email: matthew@matthewwilkes.co.uk
License: BSD
Platform: UNKNOWN
Classifier: Programming Language :: Python
Classifier: Topic :: Software Development :: Libraries :: Python Modules
